excitation_rk4_sparse/__init__.py
excitation_rk4_sparse/rk4_sparse.py
excitation_rk4_sparse/utils.py
python/_excitation_rk4_sparse.cpython-310-aarch64-linux-gnu.so
excitation_rk4_sparse-0.2.0.dist-info/LICENSE
excitation_rk4_sparse-0.2.0.dist-info/METADATA
excitation_rk4_sparse-0.2.0.dist-info/WHEEL
excitation_rk4_sparse-0.2.0.dist-info/top_level.txt
excitation_rk4_sparse-0.2.0.dist-info/RECORD
