Metadata-Version: 2.1
Name: excitation-rk4-sparse
Version: 0.2.0
Summary: High-performance sparse matrix RK4 solver for quantum excitation dynamics
Home-page: https://github.com/1160-hrk/excitation-rk4-sparse
Author: Hiroki Tsusaka
Author-email: tsusaka4research@gmail.com
License: UNKNOWN
Project-URL: Bug Reports, https://github.com/1160-hrk/excitation-rk4-sparse/issues
Project-URL: Source, https://github.com/1160-hrk/excitation-rk4-sparse
Project-URL: Documentation, https://github.com/1160-hrk/excitation-rk4-sparse/tree/main/docs
Keywords: quantum dynamics rk4 sparse physics simulation
Platform: UNKNOWN
Classifier: Development Status :: 4 - Beta
Classifier: Intended Audience :: Science/Research
Classifier: License :: OSI Approved :: MIT License
Classifier: Programming Language :: Python :: 3
Classifier: Programming Language :: Python :: 3.8
Classifier: Programming Language :: Python :: 3.9
Classifier: Programming Language :: Python :: 3.10
Classifier: Programming Language :: Python :: 3.11
Classifier: Programming Language :: C++
Classifier: Topic :: Scientific/Engineering :: Physics
Classifier: Topic :: Scientific/Engineering :: Mathematics
Classifier: Operating System :: OS Independent
Requires-Python: >=3.8
License-File: LICENSE
Requires-Dist: matplotlib (>=3.3.0)
Requires-Dist: numpy (>=1.20.0)
Requires-Dist: scipy (>=1.7.0)
Provides-Extra: benchmark
Requires-Dist: jupyter (>=1.0) ; extra == 'benchmark'
Requires-Dist: line-profiler (>=3.0) ; extra == 'benchmark'
Requires-Dist: memory-profiler (>=0.58) ; extra == 'benchmark'
Requires-Dist: seaborn (>=0.11) ; extra == 'benchmark'
Provides-Extra: dev
Requires-Dist: black (>=22.0) ; extra == 'dev'
Requires-Dist: flake8 (>=4.0) ; extra == 'dev'
Requires-Dist: pytest-cov (>=2.0) ; extra == 'dev'
Requires-Dist: pytest (>=6.0) ; extra == 'dev'
